Qlearning.py
Simple_Q-1.0.1.dist-info/LICENSE
Simple_Q-1.0.1.dist-info/METADATA
Simple_Q-1.0.1.dist-info/WHEEL
Simple_Q-1.0.1.dist-info/top_level.txt
Simple_Q-1.0.1.dist-info/RECORD
