Metadata-Version: 2.1
Name: Simple-Q
Version: 1.0.1
Summary: A low learning curve implementation of a Q-Learning algorithm.
Author-email: Nesta <nesta110402@gmail.com>
License: Copyright (c) 2018 The Python Packaging Authority
Project-URL: Homepage, https://github.com/Nesta-gitU/Simple-Q
Classifier: License :: OSI Approved :: MIT License
Classifier: Programming Language :: Python
Classifier: Programming Language :: Python :: 3
Requires-Python: >=3.9
License-File: LICENSE
Requires-Dist: numpy
Requires-Dist: bidict
